{
    "/assets/dashboard/js/bundle.administration.js": "/assets/dashboard/js/bundle.administration.js?id=9a16b23a99c4632f3bda",
    "/assets/dashboard/js/bundle.student.js": "/assets/dashboard/js/bundle.student.js?id=eb3e8606a577d8e50216",
    "/assets/dashboard/js/bundle.tutor.js": "/assets/dashboard/js/bundle.tutor.js?id=46df62cdbd80f098597f",
    "/assets/js/app.js": "/assets/js/app.js?id=c5d4d4fc84afa73866bc",
    "/assets/css/app.css": "/assets/css/app.css?id=d303b5c9007930987f4c",
    "/assets/dashboard/css/app.css": "/assets/dashboard/css/app.css?id=a84ee4438ac428da7afa"
}
